slurm_factory/__init__.py
slurm_factory/config.py
slurm_factory/constants.py
slurm_factory/exceptions.py
slurm_factory/main.py
slurm_factory/spack_yaml.py
slurm_factory/utils.py
slurm_factory/builders/__init__.py
slurm_factory/builders/slurm_builder.py
slurm_factory/commands/__init__.py
slurm_factory/commands/build_slurm/__init__.py
slurm_factory/commands/build_slurm/build.py
slurm_factory-0.1.29.data/data/share/slurm-factory/slurm_assets/slurm_install.sh
slurm_factory-0.1.29.data/data/share/slurm-factory/slurm_assets/defaults/slurmctld
slurm_factory-0.1.29.data/data/share/slurm-factory/slurm_assets/defaults/slurmd
slurm_factory-0.1.29.data/data/share/slurm-factory/slurm_assets/defaults/slurmdbd
slurm_factory-0.1.29.data/data/share/slurm-factory/slurm_assets/defaults/slurmrestd
slurm_factory-0.1.29.data/data/share/slurm-factory/slurm_assets/mysql/slurm.cnf
slurm_factory-0.1.29.data/data/share/slurm-factory/slurm_assets/nsswitch/nsswitch.conf
slurm_factory-0.1.29.data/data/share/slurm-factory/slurm_assets/profile.d/z00_lmod.sh
slurm_factory-0.1.29.data/data/share/slurm-factory/slurm_assets/slurm/acct_gather.conf
slurm_factory-0.1.29.data/data/share/slurm-factory/slurm_assets/slurm/cgroup.conf
slurm_factory-0.1.29.data/data/share/slurm-factory/slurm_assets/slurm/oci.conf
slurm_factory-0.1.29.data/data/share/slurm-factory/slurm_assets/slurm/slurm.conf
slurm_factory-0.1.29.data/data/share/slurm-factory/slurm_assets/slurm/slurmdbd.conf
slurm_factory-0.1.29.data/data/share/slurm-factory/slurm_assets/ssh/vantage_sshd.conf
slurm_factory-0.1.29.data/data/share/slurm-factory/slurm_assets/sssd/sssd.conf
slurm_factory-0.1.29.data/data/share/slurm-factory/slurm_assets/systemd/slurmctld.service
slurm_factory-0.1.29.data/data/share/slurm-factory/slurm_assets/systemd/slurmd.service
slurm_factory-0.1.29.data/data/share/slurm-factory/slurm_assets/systemd/slurmdbd.service
slurm_factory-0.1.29.data/data/share/slurm-factory/slurm_assets/systemd/slurmrestd.service
slurm_factory-0.1.29.dist-info/METADATA
slurm_factory-0.1.29.dist-info/WHEEL
slurm_factory-0.1.29.dist-info/entry_points.txt
slurm_factory-0.1.29.dist-info/licenses/LICENSE
slurm_factory-0.1.29.dist-info/RECORD
