Metadata-Version: 2.4
Name: slurm-factory
Version: 0.1.29
Summary: Slurm builder project by Vantage Compute - builds Slurm packages in Docker containers
Author-email: James Beedy <james@vantagecompute.ai>
License: MIT
License-File: LICENSE
Requires-Python: >=3.14
Requires-Dist: boto3>=1.35.0
Requires-Dist: pyyaml>=6.0.3
Requires-Dist: rich>=14.1.0
Requires-Dist: typer>=0.19.2
Provides-Extra: dev
Requires-Dist: black>=25.9.0; extra == 'dev'
Requires-Dist: codespell>=2.4.0; extra == 'dev'
Requires-Dist: mypy>=1.18.2; extra == 'dev'
Requires-Dist: pyright>=1.1.406; extra == 'dev'
Requires-Dist: pytest-cov>=7.0.0; extra == 'dev'
Requires-Dist: pytest>=8.4.2; extra == 'dev'
Requires-Dist: ruff>=0.14.0; extra == 'dev'
Requires-Dist: types-pyyaml>=6.0.12.20250915; extra == 'dev'
